mfd_mount/__init__.py
mfd_mount/base.py
mfd_mount/esxi.py
mfd_mount/exceptions.py
mfd_mount/freebsd.py
mfd_mount/posix.py
mfd_mount/windows.py
mfd_mount-1.8.0.dist-info/licenses/AUTHORS.md
mfd_mount-1.8.0.dist-info/licenses/LICENSE.md
mfd_mount-1.8.0.dist-info/METADATA
mfd_mount-1.8.0.dist-info/WHEEL
mfd_mount-1.8.0.dist-info/top_level.txt
mfd_mount-1.8.0.dist-info/RECORD
