Metadata-Version: 2.4
Name: mfd-mount
Version: 1.8.0
Summary: Module for handling mounting and unmounting fileshares on different operating systems
Project-URL: Homepage, https://github.com/intel/mfd
Project-URL: Repository, https://github.com/intel/mfd-mount
Project-URL: Issues, https://github.com/intel/mfd-mount/issues
Project-URL: Changelog, https://github.com/intel/mfd-mount/blob/main/CHANGELOG.md
Requires-Python: <3.14,>=3.10
License-File: LICENSE.md
License-File: AUTHORS.md
Requires-Dist: mfd-typing>=1.23.0
Dynamic: license-file
